refinery/__init__.py
refinery/api_calls.py
refinery/authentication.py
refinery/cli.py
refinery/exceptions.py
refinery/settings.py
refinery/util.py
refinery/adapter/__init__.py
refinery/adapter/rasa.py
refinery/adapter/sklearn.py
refinery/adapter/torch.py
refinery/adapter/transformers.py
refinery/adapter/util.py
refinery/callbacks/__init__.py
refinery/callbacks/inference.py
refinery/callbacks/sklearn.py
refinery/callbacks/torch.py
refinery/callbacks/transformers.py
refinery_python_sdk-1.4.0.dist-info/LICENSE
refinery_python_sdk-1.4.0.dist-info/METADATA
refinery_python_sdk-1.4.0.dist-info/WHEEL
refinery_python_sdk-1.4.0.dist-info/entry_points.txt
refinery_python_sdk-1.4.0.dist-info/top_level.txt
refinery_python_sdk-1.4.0.dist-info/RECORD
