Metadata-Version: 2.1
Name: refinery-python-sdk
Version: 1.4.0
Summary: Official Python SDK for Kern AI refinery.
Home-page: https://github.com/code-kern-ai/refinery-python
Author: jhoetter
Author-email: johannes.hoetter@kern.ai
License: UNKNOWN
Keywords: Kern AI,refinery,machine-learning,supervised-learning,data-centric-ai,data-annotation,python
Platform: UNKNOWN
Classifier: Development Status :: 4 - Beta
Classifier: Programming Language :: Python :: 3
Classifier: License :: OSI Approved :: Apache Software License
License-File: LICENSE
Requires-Dist: numpy
Requires-Dist: pandas
Requires-Dist: requests
Requires-Dist: boto3
Requires-Dist: botocore
Requires-Dist: spacy
Requires-Dist: wasabi
Requires-Dist: embedders
Requires-Dist: datasets
